Intro_Processor_Architecture/PROJECT(s)/IPA_Project(b)/sequential(1)/sequential/pipeline_processor/Forwarding_unit.v

module forwarding_unit(
    input [4:0] id_ex_Rs1, 
    input [4:0] id_ex_Rs2, 
    input [4:0] ex_mem_rd,
    input [4:0] mem_wb_rd,
    input ex_mem_Regwrite,
    input mem_wb_Regwrite,

    output reg [1:0] forwardA,  
    output reg [1:0] forwardB
);

always @(*) begin
    // Default forwarding values (no forwarding)
    forwardA = 2'b00;
    forwardB = 2'b00;

    // Check for EX hazard (forward from EX/MEM stage)
    if (ex_mem_Regwrite && (ex_mem_rd != 5'b00000)) begin
        if (ex_mem_rd == id_ex_Rs1) begin
            forwardA = 2'b10;
        end
        if (ex_mem_rd == id_ex_Rs2) begin
            forwardB = 2'b10;
        end
    end

    // Check for MEM hazard (forward from MEM/WB stage)
    if (mem_wb_Regwrite && (mem_wb_rd != 5'b00000)) begin
        if ((mem_wb_rd == id_ex_Rs1) && 
            !(ex_mem_Regwrite && (ex_mem_rd != 5'b00000) && (ex_mem_rd == id_ex_Rs1))) begin
            forwardA = 2'b01;
        end

        if ((mem_wb_rd == id_ex_Rs2) && 
            !(ex_mem_Regwrite && (ex_mem_rd != 5'b00000) && (ex_mem_rd == id_ex_Rs2))) begin
            forwardB = 2'b01;
        end
    end
end

endmodule

Intro_Processor_Architecture/PROJECT(s)/IPA_Project(b)/sequential(1)/sequential/pipeline_processor/Forwarding_unit_tb.v
`include "Forwarding_unit.v"
`timescale 1ns / 1ps

module forwarding_unit_tb;

    // Inputs
    reg [4:0] id_ex_Rs1;
    reg [4:0] id_ex_Rs2;
    reg [4:0] ex_mem_rd;
    reg [4:0] mem_wb_rd;
    reg ex_mem_Regwrite;
    reg mem_wb_Regwrite;

    // Outputs
    wire [1:0] forwardA;
    wire [1:0] forwardB;

    // Instantiate the forwarding unit
    forwarding_unit uut (
        .id_ex_Rs1(id_ex_Rs1),
        .id_ex_Rs2(id_ex_Rs2),
        .ex_mem_rd(ex_mem_rd),
        .mem_wb_rd(mem_wb_rd),
        .ex_mem_Regwrite(ex_mem_Regwrite),
        .mem_wb_Regwrite(mem_wb_Regwrite),
        .forwardA(forwardA),
        .forwardB(forwardB)
    );

    // Stimulus
    initial begin
        $dumpfile("forwarding_unit_tb.vcd");  // VCD dump for waveform analysis
        $dumpvars(0, forwarding_unit_tb);

        // Test 1: No forwarding (Rs1 and Rs2 do not match EX/MEM or MEM/WB)
        id_ex_Rs1 = 5'd1; id_ex_Rs2 = 5'd2;
        ex_mem_rd = 5'd3; mem_wb_rd = 5'd4;
        ex_mem_Regwrite = 1'b0; mem_wb_Regwrite = 1'b0;
        #10;
        
        // Test 2: Forward from EX/MEM stage to Rs1
        ex_mem_rd = 5'd1; ex_mem_Regwrite = 1'b1;
        #10;

        // Test 3: Forward from EX/MEM stage to Rs2
        ex_mem_rd = 5'd2;
        #10;

        // Test 4: Forward from MEM/WB stage to Rs1 (EX/MEM doesn't match)
        ex_mem_rd = 5'd3; ex_mem_Regwrite = 1'b0;
        mem_wb_rd = 5'd1; mem_wb_Regwrite = 1'b1;
        #10;

        // Test 5: Forward from MEM/WB stage to Rs2 (EX/MEM doesn't match)
        mem_wb_rd = 5'd2;
        #10;

        // Test 6: EX/MEM has priority over MEM/WB (forwarding from EX/MEM)
        ex_mem_rd = 5'd1; ex_mem_Regwrite = 1'b1;
        mem_wb_rd = 5'd1; mem_wb_Regwrite = 1'b1;
        #10;

        // Test 7: Edge case where rd = 0 (No forwarding should happen)
        id_ex_Rs1 = 5'd0; id_ex_Rs2 = 5'd0;
        ex_mem_rd = 5'd0; mem_wb_rd = 5'd0;
        ex_mem_Regwrite = 1'b1; mem_wb_Regwrite = 1'b1;
        #10;

        // Test 8: Both Rs1 and Rs2 get forwarded from EX/MEM
        id_ex_Rs1 = 5'd5; id_ex_Rs2 = 5'd6;
        ex_mem_rd = 5'd5; mem_wb_rd = 5'd6;
        ex_mem_Regwrite = 1'b1; mem_wb_Regwrite = 1'b0;
        #10;

        // Test 9: Both Rs1 and Rs2 get forwarded from MEM/WB
        ex_mem_Regwrite = 1'b0; mem_wb_Regwrite = 1'b1;
        #10;

        // End simulation
        $finish;
    end

    // Monitor output
    initial begin
        $monitor("Time=%0t | Rs1=%d, Rs2=%d | EX/MEM rd=%d, MEM/WB rd=%d | EX/MEM RW=%b, MEM/WB RW=%b | forwardA=%b, forwardB=%b",
                  $time, id_ex_Rs1, id_ex_Rs2, ex_mem_rd, mem_wb_rd, ex_mem_Regwrite, mem_wb_Regwrite, forwardA, forwardB);
    end

endmodule

// ######################### Expected outputs:------ ############################


// Time=0 | Rs1=1, Rs2=2 | EX/MEM rd=3, MEM/WB rd=4 | EX/MEM RW=0, MEM/WB RW=0 | forwardA=00, forwardB=00
// Time=10 | Rs1=1, Rs2=2 | EX/MEM rd=1, MEM/WB rd=4 | EX/MEM RW=1, MEM/WB RW=0 | forwardA=10, forwardB=00
// Time=20 | Rs1=1, Rs2=2 | EX/MEM rd=2, MEM/WB rd=4 | EX/MEM RW=1, MEM/WB RW=0 | forwardA=00, forwardB=10
// Time=30 | Rs1=1, Rs2=2 | EX/MEM rd=3, MEM/WB rd=1 | EX/MEM RW=0, MEM/WB RW=1 | forwardA=01, forwardB=00
// Time=40 | Rs1=1, Rs2=2 | EX/MEM rd=3, MEM/WB rd=2 | EX/MEM RW=0, MEM/WB RW=1 | forwardA=00, forwardB=01
// Time=50 | Rs1=1, Rs2=2 | EX/MEM rd=1, MEM/WB rd=1 | EX/MEM RW=1, MEM/WB RW=1 | forwardA=10, forwardB=00
// Time=60 | Rs1=0, Rs2=0 | EX/MEM rd=0, MEM/WB rd=0 | EX/MEM RW=1, MEM/WB RW=1 | forwardA=00, forwardB=00
// Time=70 | Rs1=5, Rs2=6 | EX/MEM rd=5, MEM/WB rd=6 | EX/MEM RW=1, MEM/WB RW=0 | forwardA=10, forwardB=00
// Time=80 | Rs1=5, Rs2=6 | EX/MEM rd=5, MEM/WB rd=6 | EX/MEM RW=0, MEM/WB RW=1 | forwardA=00, forwardB=01

Intro_Processor_Architecture/PROJECT(s)/IPA_Project(b)/sequential(1)/sequential/pipeline_processor/forwarding_unit_tb.vcd
$date
	Tue Mar  4 21:10:41 2025
$end
$version
	Icarus Verilog
$end
$timescale
	1ps
$end
$scope module forwarding_unit_tb $end
$var wire 2 ! forwardB [1:0] $end
$var wire 2 " forwardA [1:0] $end
$var reg 1 # ex_mem_Regwrite $end
$var reg 5 $ ex_mem_rd [4:0] $end
$var reg 5 % id_ex_Rs1 [4:0] $end
$var reg 5 & id_ex_Rs2 [4:0] $end
$var reg 1 ' mem_wb_Regwrite $end
$var reg 5 ( mem_wb_rd [4:0] $end
$scope module uut $end
$var wire 1 # ex_mem_Regwrite $end
$var wire 5 ) ex_mem_rd [4:0] $end
$var wire 5 * id_ex_Rs1 [4:0] $end
$var wire 5 + id_ex_Rs2 [4:0] $end
$var wire 1 ' mem_wb_Regwrite $end
$var wire 5 , mem_wb_rd [4:0] $end
$var reg 2 - forwardA [1:0] $end
$var reg 2 . forwardB [1:0] $end
$upscope $end
$upscope $end
$enddefinitions $end
#0
$dumpvars
b0 .
b0 -
b100 ,
b10 +
b1 *
b11 )
b100 (
0'
b10 &
b1 %
b11 $
0#
b0 "
b0 !
$end
#10000
b10 "
b10 -
1#
b1 $
b1 )
#20000
b10 !
b10 .
b0 "
b0 -
b10 $
b10 )
#30000
b1 "
b1 -
b0 !
b0 .
1'
b1 (
b1 ,
0#
b11 $
b11 )
#40000
b1 !
b1 .
b0 "
b0 -
b10 (
b10 ,
#50000
b10 "
b10 -
b0 !
b0 .
b1 (
b1 ,
1#
b1 $
b1 )
#60000
b0 "
b0 -
b0 (
b0 ,
b0 $
b0 )
b0 &
b0 +
b0 %
b0 *
#70000
b10 "
b10 -
0'
b110 (
b110 ,
b101 $
b101 )
b110 &
b110 +
b101 %
b101 *
#80000
b1 !
b1 .
b0 "
b0 -
1'
0#
